llm_deepseek.py
llm_deepseek-0.1.4.dist-info/LICENSE
llm_deepseek-0.1.4.dist-info/METADATA
llm_deepseek-0.1.4.dist-info/WHEEL
llm_deepseek-0.1.4.dist-info/entry_points.txt
llm_deepseek-0.1.4.dist-info/top_level.txt
llm_deepseek-0.1.4.dist-info/RECORD
