Metadata-Version: 2.2
Name: llm-deepseek
Version: 0.1.4
Summary: Access deepseek.com models via API
Author: abrasumente
License: Apache-2.0
Project-URL: Homepage, https://github.com/abrasumente233/llm-deepseek
Project-URL: Changelog, https://github.com/abrasumente233/llm-deepseek/releases
Project-URL: Issues, https://github.com/abrasumente233/llm-deepseek/issues
Project-URL: CI, https://github.com/abrasumente233/llm-deepseek/actions
Classifier: License :: OSI Approved :: Apache Software License
License-File: LICENSE
Requires-Dist: llm
Provides-Extra: test
Requires-Dist: pytest; extra == "test"
